setup.py
dualdiff/__init__.py
dualdiff/libboost_python-py27.so
dualdiff/libboost_python-py27.so.1.65.1
dualdiff/libdual.so
dualdiff.egg-info/PKG-INFO
dualdiff.egg-info/SOURCES.txt
dualdiff.egg-info/dependency_links.txt
dualdiff.egg-info/top_level.txt