Metadata-Version: 1.0
Name: dualdiff
Version: 0.1.1
Summary: Dual and Hyperdual Number Library
Home-page: UNKNOWN
Author: UNKNOWN
Author-email: UNKNOWN
License: UNKNOWN
Platform: UNKNOWN
